ethdata/__init__.py
ethdata/ethdata.py
tests/__init__.py
tests/test_arrays.py
tests/test_class_getter.py
tests/test_class_init.py
tests/test_class_setter.py
tests/test_empty_row.py
tests/test_helpers.py
tests/test_services_setup.py
eth_data_tools-0.0.4.dist-info/LICENSE
eth_data_tools-0.0.4.dist-info/METADATA
eth_data_tools-0.0.4.dist-info/WHEEL
eth_data_tools-0.0.4.dist-info/top_level.txt
eth_data_tools-0.0.4.dist-info/RECORD
